token_tools/__init__.py
token_tools/token.py
token_tools/token_funcs.py
token_tools-0.2.0.dist-info/LICENSE
token_tools-0.2.0.dist-info/METADATA
token_tools-0.2.0.dist-info/WHEEL
token_tools-0.2.0.dist-info/top_level.txt
token_tools-0.2.0.dist-info/RECORD
