Metadata-Version: 2.1
Name: token_tools
Version: 0.2.0
Summary: Token Tools provides, well, tools for Token's!
Home-page: https://github.com/salve-org/token-tools
Author: Moosems
Author-email: moosems.j@gmail.com
License: MIT license
Classifier: Development Status :: 3 - Alpha
Classifier: Operating System :: OS Independent
Classifier: Programming Language :: Python :: Implementation
Classifier: Intended Audience :: Developers
Classifier: License :: OSI Approved :: MIT License
Classifier: Typing :: Typed
Requires-Python: >=3.11
License-File: LICENSE
Requires-Dist: beartype
